JingtongPythonOpencv4Chuyi/README.md
JingtongPythonOpencv4Chuyi/__init__.py
JingtongPythonOpencv4Chuyi/__main__.py
JingtongPythonOpencv4Chuyi/file.epub
JingtongPythonOpencv4Chuyi/index.html
JingtongPythonOpencv4Chuyi/css/__init__.py
JingtongPythonOpencv4Chuyi/css/annotations.css
JingtongPythonOpencv4Chuyi/css/main.css
JingtongPythonOpencv4Chuyi/css/normalize.css
JingtongPythonOpencv4Chuyi/css/popup.css
JingtongPythonOpencv4Chuyi/font/__init__.py
JingtongPythonOpencv4Chuyi/font/fontello.eot
JingtongPythonOpencv4Chuyi/font/fontello.svg
JingtongPythonOpencv4Chuyi/font/fontello.ttf
JingtongPythonOpencv4Chuyi/font/fontello.woff
JingtongPythonOpencv4Chuyi/img/__init__.py
JingtongPythonOpencv4Chuyi/img/annotator-glyph-sprite.png
JingtongPythonOpencv4Chuyi/img/annotator-icon-sprite.png
JingtongPythonOpencv4Chuyi/img/apple-touch-icon.png
JingtongPythonOpencv4Chuyi/img/cancelfullscreen.png
JingtongPythonOpencv4Chuyi/img/close.png
JingtongPythonOpencv4Chuyi/img/fullscreen.png
JingtongPythonOpencv4Chuyi/img/loader.gif
JingtongPythonOpencv4Chuyi/img/menu-icon.png
JingtongPythonOpencv4Chuyi/img/save.png
JingtongPythonOpencv4Chuyi/img/saved.png
JingtongPythonOpencv4Chuyi/img/settings-s.png
JingtongPythonOpencv4Chuyi/img/settings.png
JingtongPythonOpencv4Chuyi/img/star.png
JingtongPythonOpencv4Chuyi/js/__init__.py
JingtongPythonOpencv4Chuyi/js/epub.js
JingtongPythonOpencv4Chuyi/js/epub.min.js
JingtongPythonOpencv4Chuyi/js/epub.min.map
JingtongPythonOpencv4Chuyi/js/hooks.min.js
JingtongPythonOpencv4Chuyi/js/hooks.min.map
JingtongPythonOpencv4Chuyi/js/reader.js
JingtongPythonOpencv4Chuyi/js/reader.js.map
JingtongPythonOpencv4Chuyi/js/reader.min.js
JingtongPythonOpencv4Chuyi/js/reader.min.map
JingtongPythonOpencv4Chuyi/js/hooks/__init__.py
JingtongPythonOpencv4Chuyi/js/hooks/extensions/__init__.py
JingtongPythonOpencv4Chuyi/js/hooks/extensions/highlight.js
JingtongPythonOpencv4Chuyi/js/libs/__init__.py
JingtongPythonOpencv4Chuyi/js/libs/jquery.min.js
jingtong_python_opencv4_chuyi-2024.3.6.0.dist-info/METADATA
jingtong_python_opencv4_chuyi-2024.3.6.0.dist-info/WHEEL
jingtong_python_opencv4_chuyi-2024.3.6.0.dist-info/entry_points.txt
jingtong_python_opencv4_chuyi-2024.3.6.0.dist-info/top_level.txt
jingtong_python_opencv4_chuyi-2024.3.6.0.dist-info/RECORD
